{
	"class" : {
		"addDefaultEnvironment" : "brunobb 10/03/2018 12:27",
		"cache" : "brunobb 10/03/2018 12:27",
		"getEnvironmentNamed:ifNone:" : "brunobb 10/03/2018 12:27",
		"getExistingEnvironmentOrCreateNewNamed:" : "brunobb 10/03/2018 12:27",
		"includesEnvironmentNamed:" : "brunobb 10/03/2018 12:27",
		"initializeCache" : "brunobb 10/03/2018 12:27",
		"newNamed:" : "brunobb 10/03/2018 12:27" },
	"instance" : {
		"addToCache" : "brunobb 11/28/2018 06:38",
		"applications" : "brunobb 10/03/2018 12:27",
		"applications:" : "brunobb 10/03/2018 12:27",
		"canDelete" : "brunobb 10/03/2018 12:27",
		"getBIApplicationName" : "brunobb 10/04/2018 03:08",
		"getBILogoSymbol" : "brunobb 10/04/2018 06:07",
		"getBackofficeApplicationName" : "brunobb 10/04/2018 03:07",
		"getBackofficeLogoSymbol" : "brunobb 10/04/2018 06:07",
		"getFrontofficeApplicationName" : "brunobb 10/04/2018 03:08",
		"getFrontofficeLogoSymbol" : "brunobb 10/04/2018 06:07",
		"includesApplication:" : "brunobb 10/03/2018 12:27",
		"includesApplicationName:" : "brunobb 10/03/2018 12:27",
		"includesUserNamed:" : "brunobb 10/03/2018 12:27",
		"initialize" : "brunobb 10/03/2018 12:27",
		"name" : "brunobb 10/03/2018 12:27",
		"name:" : "brunobb 10/03/2018 12:27",
		"printOn:" : "brunobb 10/03/2018 12:27",
		"registerApplication:" : "brunobb 10/03/2018 12:27",
		"registerUser:" : "brunobb 10/03/2018 12:27",
		"registerUser:ifPresent:" : "brunobb 10/03/2018 12:27",
		"removeFromCache" : "brunobb 10/03/2018 12:27",
		"setBIApplicationName:" : "brunobb 10/04/2018 03:06",
		"setBILogo:" : "brunobb 10/03/2018 12:45",
		"setBackofficeApplicationName:" : "brunobb 10/04/2018 03:06",
		"setBackofficeLogo:" : "brunobb 10/04/2018 06:09",
		"setFrontofficeApplicationName:" : "brunobb 10/04/2018 03:06",
		"setFrontofficeLogo:" : "brunobb 10/03/2018 12:45",
		"unregisterApplication:" : "brunobb 10/03/2018 12:27",
		"unregisterUser:" : "brunobb 10/03/2018 12:27",
		"users" : "brunobb 10/03/2018 12:27",
		"users:" : "brunobb 10/03/2018 12:27" } }
