{
	"category" : "OrbeonBPMRuntime",
	"classinstvars" : [
		 ],
	"classvars" : [
		 ],
	"commentStamp" : "",
	"instvars" : [
		"senderAppName",
		"senderProcessName",
		"senderId",
		"receiverProcessName",
		"receiverAppName",
		"receiverProcessId",
		"receiverProcessIdField",
		"receiverIdentificationFields",
		"receiverProcessDefinition",
		"receiverGatewayName",
		"receiverEventName",
		"variablesToSet" ],
	"name" : "BpmInterProcessMessage",
	"pools" : [
		 ],
	"super" : "BpmObject",
	"type" : "normal" }
