{
	"class" : {
		 },
	"instance" : {
		"addToParentProcess" : "BrunoBB 10/27/2015 17:22",
		"createProcessInstance:" : "BrunoBB 12/01/2015 11:51",
		"initialize" : "BrunoBB 06/26/2016 14:11",
		"instanceClass" : "BrunoBB 12/01/2015 12:59",
		"isEmbedded" : "BrunoBB 06/26/2016 14:11",
		"isEmbedded:" : "BrunoBB 06/26/2016 14:11",
		"isSubprocessDefinition" : "BrunoBB 12/11/2015 06:43",
		"printNameAndDefinitionType" : "BrunoBB 03/21/2016 15:51",
		"printOnType" : "BrunoBB 10/28/2015 14:15",
		"setRolesOfUnderlineProcess" : "BrunoBB 06/29/2016 11:10",
		"setSubProcessDefinition:" : "BrunoBB 06/27/2016 12:48",
		"subProcessDefinition" : "BrunoBB 10/27/2015 17:10",
		"subProcessDefinition:" : "BrunoBB 10/27/2015 17:10" } }
