{
	"class" : {
		 },
	"instance" : {
		"areActionsAvailable" : "brunobb 11/12/2019 02:27",
		"areActionsAvailable:" : "brunobb 11/12/2019 02:27",
		"assignationComposite" : "brunobb 04/24/2019 07:27",
		"assignationComposite:" : "brunobb 04/24/2019 07:27",
		"buildEditUrlFor:with:" : "brunobb 05/15/2019 13:09",
		"buildNewUrlFor:with:" : "brunobb 05/13/2019 13:34",
		"buildPDFUrlFor:with:" : "brunobb 05/13/2019 13:34",
		"buildViewUrlFor:with:" : "brunobb 05/13/2019 13:34",
		"canEditTask:" : "brunobb 11/12/2019 03:02",
		"clearAssignationCompostite" : "brunobb 04/24/2019 07:27",
		"closeAndSendForm:" : "brunobb 08/22/2019 11:57",
		"closeSendAndSelectUsers:" : "brunobb 04/24/2019 07:27",
		"closeSendAndTakeNextForms:" : "brunobb 11/12/2019 02:25",
		"createOrbeonLinkOn:for:" : "brunobb 11/12/2019 02:25",
		"createSeasideLinkOn:for:" : "brunobb 11/12/2019 02:25",
		"downloadXPDLFile" : "brunobb 11/12/2019 02:25",
		"finalizeAndLoop:" : "brunobb 08/22/2019 13:11",
		"freeSelectedAssignment" : "brunobb 11/12/2019 02:25",
		"getAllTasks" : "brunobb 11/12/2019 02:25",
		"getSeasideKurlParameter" : "brunobb 04/24/2019 07:30",
		"getUrlFor:with:" : "brunobb 11/12/2019 02:25",
		"gitbookUrl" : "brunobb 11/12/2019 02:25",
		"iconFor:" : "brunobb 11/12/2019 02:25",
		"imageTitleFor:" : "brunobb 11/12/2019 02:25",
		"initialize" : "brunobb 11/12/2019 03:04",
		"innerSeasideComponent" : "brunobb 04/24/2019 07:27",
		"innerSeasideComponent:" : "brunobb 04/24/2019 07:27",
		"isBannerAvailable" : "brunobb 11/12/2019 02:25",
		"isBannerAvailable:" : "brunobb 11/12/2019 02:25",
		"linkToOrbeonFormFor:" : "brunobb 11/12/2019 02:25",
		"linkToOrbeonPdfFor:" : "brunobb 11/12/2019 02:25",
		"linkToSeasideComponentFor:" : "brunobb 11/12/2019 02:25",
		"model:" : "brunobb 11/12/2019 02:25",
		"portalComponent" : "brunobb 04/24/2019 07:32",
		"removeSelectionAndRefreshLateralCollection" : "brunobb 11/12/2019 02:25",
		"renderCloseAndSendAndSelectUsersIconOn:for:" : "brunobb 11/12/2019 02:25",
		"renderCloseAndSendAndTakeNextIconOn:for:" : "brunobb 11/12/2019 02:25",
		"renderCloseAndSendFormOn:for:" : "brunobb 11/12/2019 02:25",
		"renderCloseAndSendIconOn:for:" : "brunobb 11/12/2019 02:25",
		"renderCloseAndSendRegularIconOn:for:" : "brunobb 11/12/2019 02:25",
		"renderContentOn:" : "brunobb 11/12/2019 02:25",
		"renderFormDataOn:for:" : "brunobb 11/12/2019 02:25",
		"renderItemComponentOn:" : "brunobb 11/12/2019 02:25",
		"renderItemDescriptionAditionalDataOn:" : "brunobb 11/12/2019 02:25",
		"renderItemDescriptionOn:" : "brunobb 11/12/2019 02:25",
		"renderItemDescriptionSecondaryDataOn:" : "brunobb 11/12/2019 02:25",
		"renderItemDescriptionTitleOn:" : "brunobb 11/12/2019 02:25",
		"renderOrbeonLinkIconOn:for:" : "brunobb 11/12/2019 02:25",
		"renderReleaseAssignmentOn:" : "brunobb 11/12/2019 02:25",
		"renderSeasideFormLinkIconOn:for:" : "brunobb 11/12/2019 02:25",
		"renderStandardLoopIconOn:for:" : "brunobb 08/22/2019 13:17",
		"renderStandardLoopOn:for:" : "brunobb 08/30/2019 12:28",
		"renderSvgProcessMapOn:" : "brunobb 11/12/2019 02:25",
		"renderTransitionActionsOn:for:" : "brunobb 11/12/2019 02:25",
		"renderTransitionDataOn:for:" : "brunobb 11/12/2019 02:25",
		"renderTransitionFormDataOn:for:" : "brunobb 11/12/2019 03:00",
		"renderTransitionSubProcessDataOn:for:" : "brunobb 11/12/2019 02:25",
		"renderTransitionSummaryOn:for:" : "brunobb 11/12/2019 02:25",
		"renderTriggerErrorEventOn:from:event:" : "brunobb 08/12/2019 10:43",
		"triggerErrorEvent:from:in:" : "brunobb 08/12/2019 10:46",
		"userIsTaskOwner" : "brunobb 11/12/2019 02:25",
		"userIsTaskOwner:" : "brunobb 11/12/2019 02:25",
		"viewSvgProcessMap" : "brunobb 11/12/2019 02:25" } }
