{
	"class" : {
		"exampleMultipleProcesses" : "brunobb 10/15/2017 19:44",
		"exampleMultipleProcesses2" : "brunobb 10/15/2017 19:44",
		"exampleMultipleProcesses3" : "brunobb 10/15/2017 19:44",
		"forFiles:" : "brunobb 10/15/2017 20:01",
		"forProcessNamed:withString:" : "brunobb 10/15/2017 20:10" },
	"instance" : {
		"addXPDLDocument:namedAs:" : "brunobb 10/15/2017 20:05",
		"connectProcesses" : "BrunoBB 01/21/2016 12:19",
		"connectSubProcesses" : "BrunoBB 01/21/2016 12:19",
		"getAllLanes" : "brunobb 10/16/2017 07:01",
		"getAllPools" : "brunobb 10/16/2017 07:00",
		"getAllSubProcessNodes" : "BrunoBB 01/21/2016 12:19",
		"getAllWorkflows" : "BrunoBB 01/21/2016 11:08",
		"getDiagramDimensions" : "brunobb 02/12/2018 09:25",
		"getImportWarningReport" : "brunobb 10/09/2018 05:49",
		"getImportWarningReportWith:" : "brunobb 10/15/2017 20:25",
		"getPackageFrom:" : "BrunoBB 01/21/2016 12:19",
		"getPackageNameFrom:" : "BrunoBB 01/21/2016 12:19",
		"getPackageNamed:" : "BrunoBB 01/21/2016 12:19",
		"getPoolsWithoutLanes" : "brunobb 10/16/2017 07:22",
		"getSubProcessNodesWithoutProcessDefinition" : "BrunoBB 01/21/2016 10:52",
		"hasParentProcess:" : "BrunoBB 01/21/2016 12:19",
		"hasWarnings" : "BrunoBB 01/22/2016 11:33",
		"importReport" : "BrunoBB 01/21/2016 12:20",
		"importReport:" : "BrunoBB 01/21/2016 12:20",
		"initialize" : "BrunoBB 01/22/2016 11:28",
		"xpdlDocuments" : "BrunoBB 01/21/2016 12:19",
		"xpdlDocuments:" : "BrunoBB 01/21/2016 12:19",
		"xpdlPackages" : "BrunoBB 01/21/2016 12:19",
		"xpdlPackages:" : "BrunoBB 01/21/2016 12:19" } }
